odoo/addons/base_ubl_payment/README.rst
odoo/addons/base_ubl_payment/__init__.py
odoo/addons/base_ubl_payment/__manifest__.py
odoo/addons/base_ubl_payment/i18n/base_ubl_payment.pot
odoo/addons/base_ubl_payment/i18n/hr.po
odoo/addons/base_ubl_payment/i18n/nl.po
odoo/addons/base_ubl_payment/models/__init__.py
odoo/addons/base_ubl_payment/models/ubl.py
odoo/addons/base_ubl_payment/readme/CONTRIBUTORS.rst
odoo/addons/base_ubl_payment/readme/DESCRIPTION.rst
odoo/addons/base_ubl_payment/static/description/icon.png
odoo/addons/base_ubl_payment/static/description/index.html
odoo13_addon_base_ubl_payment-13.0.1.0.1.dist-info/METADATA
odoo13_addon_base_ubl_payment-13.0.1.0.1.dist-info/WHEEL
odoo13_addon_base_ubl_payment-13.0.1.0.1.dist-info/top_level.txt
odoo13_addon_base_ubl_payment-13.0.1.0.1.dist-info/RECORD
