Metadata-Version: 2.1
Name: odoo13-addon-base-ubl-payment
Version: 13.0.1.0.1
Summary: Payment-related code for Universal Business Language (UBL)
Home-page: https://github.com/OCA/edi
Author: Akretion,Odoo Community Association (OCA)
Author-email: support@odoo-community.org
License: AGPL-3
Platform: UNKNOWN
Classifier: Programming Language :: Python
Classifier: Framework :: Odoo
Classifier: Framework :: Odoo :: 13.0
Classifier: License :: OSI Approved :: GNU Affero General Public License v3
Requires-Python: >=3.5
Requires-Dist: lxml
Requires-Dist: odoo13-addon-account-payment-unece
Requires-Dist: odoo13-addon-base-ubl
Requires-Dist: odoo (<13.1dev,>=13.0a)
